skfdiff
