Metadata-Version: 2.1
Name: skfdiff
Version: 0.6.0
Summary: Automatic finite difference discretization for 1D PDE with fast temporal solvers.
Home-page: https://gitlab.com/celliern/scikit-fdiff/
Author: N. Cellier
Author-email: contact@nicolas-cellier.net
License: MIT
Keywords: PDE,finite-difference,physic,modelling,interactive
Platform: UNKNOWN
Classifier: Programming Language :: Python :: 3
Classifier: Programming Language :: Python :: 3.6
Classifier: Programming Language :: Python :: 3.7
Requires-Python: >= 3.6
Provides-Extra: interactive
Provides-Extra: docs
Provides-Extra: numba
Provides-Extra: dev
